gladlang/__init__.py
gladlang/__main__.py
gladlang/constants.py
gladlang/errors.py
gladlang/interpreter.py
gladlang/lexer.py
gladlang/nodes.py
gladlang/parser.py
gladlang/runtime.py
gladlang/values.py
gladlang-0.1.6.dist-info/licenses/LICENSE
gladlang-0.1.6.dist-info/METADATA
gladlang-0.1.6.dist-info/WHEEL
gladlang-0.1.6.dist-info/entry_points.txt
gladlang-0.1.6.dist-info/top_level.txt
gladlang-0.1.6.dist-info/RECORD
