Metadata-Version: 2.4
Name: gladlang
Version: 0.1.6
Summary: The GladLang Interpreter
Author: Glad432
License: Copyright (c) 2025 - present GLAD432
Project-URL: homepage, https://github.com/gladw-in/gladlang
Project-URL: documentation, https://gladlang.pages.dev/
Project-URL: source, https://github.com/gladw-in/gladlang
Keywords: interpreter,language,compiler,educational
Classifier: Development Status :: 4 - Beta
Classifier: Intended Audience :: Developers
Classifier: Programming Language :: Python :: 3
Classifier: Programming Language :: Python :: 3.10
Classifier: Programming Language :: Python :: 3.14
Classifier: License :: OSI Approved :: MIT License
Classifier: Operating System :: OS Independent
Requires-Python: >=3.10
License-File: LICENSE
Dynamic: license-file
